{
  "warnings" : [ ],
  "files" : [ "report.json", "untyped_A.A(A__this)_-1137467753.json", "untyped_A.getOne(A__this)_-1136543333.json", "untyped_A.getPositive(A__this,_untyped_i)_-1134695237.json", "untyped_A.getPositive(A__this,_untyped_i)_-1135618727.json", "untyped_tests.main(tests__this).json" ],
  "info" : {
    "cfgs" : "5",
    "duration" : "155ms",
    "end" : "2023-03-09T09:49:30.967+01:00",
    "expressions" : "26",
    "files" : "5",
    "globals" : "0",
    "members" : "5",
    "programs" : "1",
    "start" : "2023-03-09T09:49:30.812+01:00",
    "statements" : "14",
    "units" : "2",
    "version" : "0.1b7",
    "warnings" : "0"
  },
  "configuration" : {
    "analysisGraphs" : "NONE",
    "descendingPhaseType" : "NONE",
    "fixpointWorkingSet" : "FIFOWorkingSet",
    "glbThreshold" : "5",
    "jsonOutput" : "true",
    "openCallPolicy" : "WorstCasePolicy",
    "semanticChecks" : "",
    "serializeInputs" : "false",
    "serializeResults" : "true",
    "syntacticChecks" : "",
    "wideningThreshold" : "5",
    "workdir" : "test-outputs/interprocedural/RTAContextSensitive1"
  }
}