{"name":"untyped errors::tryCatchMultiInstructions(errors* this)","description":null,"nodes":[{"id":0,"subNodes":[1,2],"text":"x = 10"},{"id":1,"text":"x"},{"id":2,"text":"10"},{"id":3,"subNodes":[4,5],"text":"x = 7"},{"id":4,"text":"x"},{"id":5,"text":"7"},{"id":6,"subNodes":[7,8],"text":"x = 5"},{"id":7,"text":"x"},{"id":8,"text":"5"},{"id":9,"subNodes":[10,11],"text":"x = 4"},{"id":10,"text":"x"},{"id":11,"text":"4"},{"id":12,"subNodes":[13,14],"text":"x = 3"},{"id":13,"text":"x"},{"id":14,"text":"3"},{"id":15,"subNodes":[16,17],"text":"x = 9"},{"id":16,"text":"x"},{"id":17,"text":"9"},{"id":18,"text":"ret"}],"edges":[{"sourceId":0,"destId":3,"kind":"SequentialEdge","label":null},{"sourceId":3,"destId":6,"kind":"SequentialEdge","label":null},{"sourceId":3,"destId":15,"kind":"ErrorEdge","label":"A"},{"sourceId":6,"destId":9,"kind":"SequentialEdge","label":null},{"sourceId":6,"destId":15,"kind":"ErrorEdge","label":"A"},{"sourceId":9,"destId":12,"kind":"SequentialEdge","label":null},{"sourceId":9,"destId":15,"kind":"ErrorEdge","label":"A"},{"sourceId":12,"destId":15,"kind":"ErrorEdge","label":"A"},{"sourceId":12,"destId":18,"kind":"SequentialEdge","label":null},{"sourceId":15,"destId":18,"kind":"SequentialEdge","label":null}],"descriptions":[]}