{
  "warnings" : [ ],
  "files" : [ "report.json", "untyped_arrays.bitest(arrays__this).json", "untyped_arrays.test(arrays__this).json" ],
  "info" : {
    "cfgs" : "2",
    "duration" : "781ms",
    "end" : "2025-07-09T12:58:20.799+02:00",
    "expressions" : "64",
    "files" : "2",
    "globals" : "0",
    "members" : "2",
    "programs" : "1",
    "start" : "2025-07-09T12:58:20.018+02:00",
    "statements" : "19",
    "units" : "1",
    "version" : "0.1",
    "warnings" : "0"
  },
  "configuration" : {
    "analysisGraphs" : "NONE",
    "descendingPhaseType" : "NONE",
    "dumpForcesUnwinding" : "false",
    "fixpointWorkingSet" : "OrderBasedWorkingSet",
    "glbThreshold" : "5",
    "hotspots" : "unset",
    "jsonOutput" : "true",
    "openCallPolicy" : "TopExecutionPolicy",
    "optimize" : "false",
    "recursionWideningThreshold" : "5",
    "semanticChecks" : "",
    "serializeInputs" : "false",
    "serializeResults" : "true",
    "shouldSmashError" : "unset",
    "syntacticChecks" : "",
    "useWideningPoints" : "true",
    "wideningThreshold" : "5",
    "workdir" : "test-outputs/arrays/allocations"
  }
}